mylib019/__init__.py
mylib019-0.1.dist-info/LICENSE.txt
mylib019-0.1.dist-info/METADATA
mylib019-0.1.dist-info/WHEEL
mylib019-0.1.dist-info/top_level.txt
mylib019-0.1.dist-info/RECORD
